japre/__init__.py
japre/ipadic.py
japre/manbyo.py
japre-0.1.4.dist-info/LICENSE
japre-0.1.4.dist-info/WHEEL
japre-0.1.4.dist-info/METADATA
japre-0.1.4.dist-info/RECORD
