Metadata-Version: 2.1
Name: japre
Version: 0.1.4
Summary: Custom pretokenizers for Japanese language models
Home-page: https://github.com/Alab-NII/japanese_pretokenizers
License: MIT
Author: Kaito Sugimoto
Author-email: kaito_sugimoto@is.s.u-tokyo.ac.jp
Requires-Python: >=3.7
Classifier: License :: OSI Approved :: MIT License
Classifier: Programming Language :: Python :: 3
Classifier: Programming Language :: Python :: 3.7
Classifier: Programming Language :: Python :: 3.8
Classifier: Programming Language :: Python :: 3.9
Requires-Dist: flake8 (>=4.0.0)
Requires-Dist: fugashi (>=1.1.0)
Requires-Dist: ipadic (>=1.0.0)
Requires-Dist: pytextspan (>=0.5.0)
Requires-Dist: tokenizers (>=0.10.0)
Project-URL: Repository, https://github.com/Alab-NII/japanese_pretokenizers
